mrml-0.2.0.dist-info/METADATA
mrml-0.2.0.dist-info/WHEEL
mrml/__init__.py
mrml/__init__.pyi
mrml/py.typed
mrml/mrml.cpython-310-arm-linux-gnueabihf.so
mrml-0.2.0.dist-info/RECORD
