Metadata-Version: 2.4
Name: mrml
Version: 0.2.0
Classifier: Programming Language :: Rust
Classifier: Programming Language :: Python :: Implementation :: CPython
Classifier: Programming Language :: Python :: Implementation :: PyPy
Summary: A Python wrapper for MRML (Rust port of MJML).
Keywords: email,mjml
Author: Jérémie Drouet <jeremie.drouet@gmail.com>
Author-email: Jérémie Drouet <jeremie.drouet@gmail.com>
License: MIT
Requires-Python: >=3.7
Project-URL: Homepage, https://github.com/jdrouet/mrml
Project-URL: Bug Tracker, https://github.com/jdrouet/mrml/issues
